gorlay_mcp_server/__init__.py
gorlay_mcp_server-0.1.0.dist-info/METADATA
gorlay_mcp_server-0.1.0.dist-info/WHEEL
gorlay_mcp_server-0.1.0.dist-info/entry_points.txt
gorlay_mcp_server-0.1.0.dist-info/RECORD
